Metadata-Version: 2.4
Name: dap-bi
Version: 4.1.4
Summary: DAP BI - Аналитика и дашборды для банковского аудита
Download-URL: https://www.apache.org/dist/superset/4.1.4
Author-email: Apache Software Foundation <dev@superset.apache.org>
License:                               Apache License
Project-URL: homepage, https://superset.apache.org/
Project-URL: documentation, https://superset.apache.org/docs/intro
Classifier: Programming Language :: Python :: 3.9
Classifier: Programming Language :: Python :: 3.10
Classifier: Programming Language :: Python :: 3.11
Requires-Python: ~=3.9
License-File: LICENSE.txt
License-File: NOTICE
Requires-Dist: backoff>=1.8.0
Requires-Dist: celery<6.0.0,>=5.3.6
Requires-Dist: click>=8.0.3
Requires-Dist: click-option-group
Requires-Dist: colorama
Requires-Dist: croniter>=0.3.28
Requires-Dist: cron-descriptor
Requires-Dist: cryptography<45.0.0,>=42.0.4
Requires-Dist: deprecation<2.2.0,>=2.1.0
Requires-Dist: flask<3.0.0,>=2.2.5
Requires-Dist: flask-appbuilder<5.0.0,>=4.5.0
Requires-Dist: flask-caching<3,>=2.1.0
Requires-Dist: flask-compress<2.0,>=1.13
Requires-Dist: flask-talisman<2.0,>=1.0.0
Requires-Dist: flask-login<1.0,>=0.6.0
Requires-Dist: flask-migrate<4.0,>=3.1.0
Requires-Dist: flask-session<1.0,>=0.4.0
Requires-Dist: flask-wtf<2.0,>=1.1.0
Requires-Dist: func_timeout
Requires-Dist: geopy
Requires-Dist: gunicorn>=22.0.0; sys_platform != "win32"
Requires-Dist: hashids<2,>=1.3.1
Requires-Dist: holidays<0.26,>=0.25
Requires-Dist: humanize
Requires-Dist: importlib_metadata
Requires-Dist: isodate
Requires-Dist: jsonpath-ng<2,>=1.6.1
Requires-Dist: Mako>=1.2.2
Requires-Dist: markdown>=3.0
Requires-Dist: marshmallow<4
Requires-Dist: msgpack<1.1,>=1.0.0
Requires-Dist: nh3<0.3,>=0.2.11
Requires-Dist: numpy==1.23.5
Requires-Dist: packaging
Requires-Dist: pandas[performance]<2.1,>=2.0.3
Requires-Dist: parsedatetime
Requires-Dist: paramiko>=3.4.0
Requires-Dist: pgsanity
Requires-Dist: polyline<3.0,>=2.0.0
Requires-Dist: pyparsing<4,>=3.0.6
Requires-Dist: python-dateutil
Requires-Dist: python-dotenv
Requires-Dist: pyarrow<15,>=14.0.1
Requires-Dist: pyyaml<7.0.0,>=6.0.0
Requires-Dist: PyJWT<3.0,>=2.4.0
Requires-Dist: redis<5.0,>=4.6.0
Requires-Dist: selenium<4.10.0,>=3.141.0
Requires-Dist: shillelagh[gsheetsapi]<2.0,>=1.2.18
Requires-Dist: shortid
Requires-Dist: sshtunnel<0.5,>=0.4.0
Requires-Dist: simplejson>=3.15.0
Requires-Dist: slack_sdk<4,>=3.19.0
Requires-Dist: sqlalchemy<2,>=1.4
Requires-Dist: sqlalchemy-utils<0.39,>=0.38.3
Requires-Dist: sqlglot<27,>=25.24.0
Requires-Dist: sqlparse>=0.5.0
Requires-Dist: tabulate<0.9,>=0.8.9
Requires-Dist: typing-extensions<5,>=4
Requires-Dist: waitress; sys_platform == "win32"
Requires-Dist: wtforms<4,>=2.3.3
Requires-Dist: wtforms-json
Requires-Dist: xlsxwriter<3.1,>=3.0.7
Requires-Dist: flask-cors>=4.0.0
Requires-Dist: asyncpg>=0.29.0
Provides-Extra: athena
Requires-Dist: pyathena[pandas]<3,>=2; extra == "athena"
Provides-Extra: aurora-data-api
Requires-Dist: preset-sqlalchemy-aurora-data-api<0.3,>=0.2.8; extra == "aurora-data-api"
Provides-Extra: bigquery
Requires-Dist: pandas-gbq>=0.19.1; extra == "bigquery"
Requires-Dist: sqlalchemy-bigquery>=1.6.1; extra == "bigquery"
Requires-Dist: google-cloud-bigquery>=3.10.0; extra == "bigquery"
Provides-Extra: clickhouse
Requires-Dist: clickhouse-connect<1.0,>=0.5.14; extra == "clickhouse"
Provides-Extra: cockroachdb
Requires-Dist: cockroachdb<0.4,>=0.3.5; extra == "cockroachdb"
Provides-Extra: cors
Requires-Dist: flask-cors>=2.0.0; extra == "cors"
Provides-Extra: crate
Requires-Dist: crate[sqlalchemy]<0.27,>=0.26.0; extra == "crate"
Provides-Extra: databend
Requires-Dist: databend-sqlalchemy<1.0,>=0.3.2; extra == "databend"
Provides-Extra: databricks
Requires-Dist: databricks-sql-connector<3,>=2.0.2; extra == "databricks"
Requires-Dist: sqlalchemy-databricks>=0.2.0; extra == "databricks"
Provides-Extra: db2
Requires-Dist: ibm-db-sa<=0.4.0,>0.3.8; extra == "db2"
Provides-Extra: dremio
Requires-Dist: sqlalchemy-dremio<1.3,>=1.1.5; extra == "dremio"
Provides-Extra: drill
Requires-Dist: sqlalchemy-drill<2,>=1.1.4; extra == "drill"
Provides-Extra: druid
Requires-Dist: pydruid<0.7,>=0.6.5; extra == "druid"
Provides-Extra: duckdb
Requires-Dist: duckdb-engine<0.10,>=0.9.5; extra == "duckdb"
Provides-Extra: dynamodb
Requires-Dist: pydynamodb>=0.4.2; extra == "dynamodb"
Provides-Extra: solr
Requires-Dist: sqlalchemy-solr>=0.2.0; extra == "solr"
Provides-Extra: elasticsearch
Requires-Dist: elasticsearch-dbapi<0.3.0,>=0.2.9; extra == "elasticsearch"
Provides-Extra: exasol
Requires-Dist: sqlalchemy-exasol<3.0,>=2.4.0; extra == "exasol"
Provides-Extra: excel
Requires-Dist: xlrd<1.3,>=1.2.0; extra == "excel"
Provides-Extra: firebird
Requires-Dist: sqlalchemy-firebird<0.8,>=0.7.0; extra == "firebird"
Provides-Extra: firebolt
Requires-Dist: firebolt-sqlalchemy<2,>=1.0.0; extra == "firebolt"
Provides-Extra: gevent
Requires-Dist: gevent>=23.9.1; extra == "gevent"
Provides-Extra: gsheets
Requires-Dist: shillelagh[gsheetsapi]<2,>=1.2.18; extra == "gsheets"
Provides-Extra: hana
Requires-Dist: hdbcli==2.4.162; extra == "hana"
Requires-Dist: sqlalchemy_hana==0.4.0; extra == "hana"
Provides-Extra: hive
Requires-Dist: pyhive[hive]>=0.6.5; python_version < "3.11" and extra == "hive"
Requires-Dist: pyhive[hive_pure_sasl]>=0.7.0; extra == "hive"
Requires-Dist: tableschema; extra == "hive"
Requires-Dist: thrift<1.0.0,>=0.14.1; extra == "hive"
Requires-Dist: thrift_sasl<1.0.0,>=0.4.3; extra == "hive"
Provides-Extra: impala
Requires-Dist: impyla<0.17,>0.16.2; extra == "impala"
Provides-Extra: kusto
Requires-Dist: sqlalchemy-kusto<3,>=2.0.0; extra == "kusto"
Provides-Extra: kylin
Requires-Dist: kylinpy<2.9,>=2.8.1; extra == "kylin"
Provides-Extra: mssql
Requires-Dist: pymssql<3,>=2.2.8; extra == "mssql"
Provides-Extra: mysql
Requires-Dist: mysqlclient<3,>=2.1.0; extra == "mysql"
Provides-Extra: ocient
Requires-Dist: sqlalchemy-ocient>=1.0.0; extra == "ocient"
Requires-Dist: pyocient<2,>=1.0.15; extra == "ocient"
Requires-Dist: shapely; extra == "ocient"
Requires-Dist: geojson; extra == "ocient"
Provides-Extra: oracle
Requires-Dist: cx-Oracle<8.1,>8.0.0; extra == "oracle"
Provides-Extra: pinot
Requires-Dist: pinotdb<6.0.0,>=5.0.0; extra == "pinot"
Provides-Extra: playwright
Requires-Dist: playwright<2,>=1.37.0; extra == "playwright"
Provides-Extra: postgres
Requires-Dist: psycopg2-binary==2.9.6; extra == "postgres"
Provides-Extra: presto
Requires-Dist: pyhive[presto]>=0.6.5; extra == "presto"
Provides-Extra: trino
Requires-Dist: trino>=0.328.0; extra == "trino"
Provides-Extra: prophet
Requires-Dist: prophet<2,>=1.1.5; extra == "prophet"
Provides-Extra: redshift
Requires-Dist: sqlalchemy-redshift<0.9,>=0.8.1; extra == "redshift"
Provides-Extra: rockset
Requires-Dist: rockset-sqlalchemy<1,>=0.0.1; extra == "rockset"
Provides-Extra: shillelagh
Requires-Dist: shillelagh[all]<2,>=1.2.18; extra == "shillelagh"
Provides-Extra: snowflake
Requires-Dist: snowflake-sqlalchemy<2,>=1.2.4; extra == "snowflake"
Provides-Extra: spark
Requires-Dist: pyhive[hive]>=0.6.5; python_version < "3.11" and extra == "spark"
Requires-Dist: pyhive[hive_pure_sasl]>=0.7; extra == "spark"
Requires-Dist: tableschema; extra == "spark"
Requires-Dist: thrift<1,>=0.14.1; extra == "spark"
Provides-Extra: teradata
Requires-Dist: teradatasql>=16.20.0.23; extra == "teradata"
Provides-Extra: thumbnails
Requires-Dist: Pillow<11,>=10.0.1; extra == "thumbnails"
Provides-Extra: vertica
Requires-Dist: sqlalchemy-vertica-python<0.6,>=0.5.9; extra == "vertica"
Provides-Extra: netezza
Requires-Dist: nzalchemy>=11.0.2; extra == "netezza"
Provides-Extra: starrocks
Requires-Dist: starrocks>=1.0.0; extra == "starrocks"
Provides-Extra: doris
Requires-Dist: pydoris<2.0.0,>=1.0.0; extra == "doris"
Provides-Extra: oceanbase
Requires-Dist: oceanbase_py>=0.0.1; extra == "oceanbase"
Provides-Extra: development
Requires-Dist: docker; extra == "development"
Requires-Dist: flask-testing; extra == "development"
Requires-Dist: freezegun; extra == "development"
Requires-Dist: greenlet>=2.0.2; extra == "development"
Requires-Dist: grpcio>=1.55.3; extra == "development"
Requires-Dist: openapi-spec-validator; extra == "development"
Requires-Dist: parameterized; extra == "development"
Requires-Dist: pip-compile-multi; extra == "development"
Requires-Dist: pre-commit; extra == "development"
Requires-Dist: progress<2,>=1.5; extra == "development"
Requires-Dist: pyfakefs; extra == "development"
Requires-Dist: pyinstrument<5,>=4.0.2; extra == "development"
Requires-Dist: pylint; extra == "development"
Requires-Dist: pytest<8.0.0; extra == "development"
Requires-Dist: pytest-cov; extra == "development"
Requires-Dist: pytest-mock; extra == "development"
Requires-Dist: python-ldap>=3.4.4; extra == "development"
Requires-Dist: ruff; extra == "development"
Requires-Dist: sqloxide; extra == "development"
Requires-Dist: statsd; extra == "development"
Requires-Dist: tox; extra == "development"
Dynamic: download-url
Dynamic: license-file
